{
  "algorithm": {
    "decoder": "DBLF",
    "name": "DBLF",
    "params": {
      "decoder": "DBLF",
      "rotation_mode": "C1_respect",
      "support_min_ratio": 1.0,
      "support_required": true
    },
    "seed": 0,
    "variant": "C1_respect"
  },
  "dataset": {
    "family": "BR-Original",
    "instance_id": "BR7_023",
    "modification_protocol": {
      "customer_assignment": null,
      "enabled": false,
      "fragile_assignment": null,
      "fragile_ratio": null,
      "n_customers": null,
      "notes": "",
      "orientation_rules": null,
      "seed": 0,
      "weight_limit": {
        "Qmax": null,
        "enabled": null,
        "note": ""
      },
      "weights": null
    },
    "source": "Bischoff-Ratcliff"
  },
  "meta": {
    "cg_summary": {
      "cg": [
        270.5968,
        109.6188,
        97.5252
      ],
      "dev": [
        23.9032,
        6.8812,
        12.4748
      ],
      "rd_pct": [
        8.1165,
        5.9066,
        11.3407
      ],
      "z1_util": 0.716006,
      "z3": 14.4197
    },
    "container": {
      "H": 220.0,
      "L": 589.0,
      "W": 233.0
    },
    "counts": {
      "placed": 124,
      "unplaced": 33
    },
    "notes": "",
    "timing": {
      "elapsed_sec": 0.310408
    }
  },
  "objectives": {
    "Z1": {
      "name": "volume_utilization",
      "sense": "max"
    },
    "Z2": {
      "name": "unloading_obstacles",
      "sense": "min"
    },
    "Z3": {
      "name": "cg_deviation_avg_axes",
      "sense": "min"
    }
  },
  "pareto_front": [
    {
      "cg": {
        "container": {
          "x": 294.5,
          "y": 116.5,
          "z": 110.0
        },
        "dev": {
          "x": 23.9032,
          "y": 6.8812,
          "z": 12.4748
        },
        "loaded": {
          "x": 270.5968,
          "y": 109.6188,
          "z": 97.5252
        },
        "rd_pct": {
          "x": 8.1165,
          "y": 5.9066,
          "z": 11.3407
        },
        "total_mass": 21617749.0,
        "z3": 14.4197
      },
      "diagnostics": {
        "elapsed_sec": 0.310408,
        "notes": "",
        "placed_count": 124,
        "unplaced_count": 33
      },
      "layout": {
        "boxes": [
          {
            "h": 23,
            "l": 84,
            "w": 81,
            "x": 0,
            "y": 0,
            "z": 0
          },
          {
            "h": 23,
            "l": 84,
            "w": 81,
            "x": 0,
            "y": 81,
            "z": 0
          },
          {
            "h": 23,
            "l": 84,
            "w": 81,
            "x": 0,
            "y": 0,
            "z": 23
          },
          {
            "h": 23,
            "l": 84,
            "w": 81,
            "x": 0,
            "y": 81,
            "z": 23
          },
          {
            "h": 115,
            "l": 72,
            "w": 64,
            "x": 0,
            "y": 162,
            "z": 0
          },
          {
            "h": 64,
            "l": 72,
            "w": 115,
            "x": 0,
            "y": 0,
            "z": 46
          },
          {
            "h": 64,
            "l": 72,
            "w": 115,
            "x": 0,
            "y": 0,
            "z": 110
          },
          {
            "h": 115,
            "l": 72,
            "w": 64,
            "x": 72,
            "y": 162,
            "z": 0
          },
          {
            "h": 49,
            "l": 77,
            "w": 25,
            "x": 0,
            "y": 115,
            "z": 46
          },
          {
            "h": 49,
            "l": 77,
            "w": 25,
            "x": 0,
            "y": 115,
            "z": 95
          },
          {
            "h": 25,
            "l": 77,
            "w": 49,
            "x": 0,
            "y": 162,
            "z": 115
          },
          {
            "h": 25,
            "l": 77,
            "w": 49,
            "x": 0,
            "y": 162,
            "z": 140
          },
          {
            "h": 49,
            "l": 77,
            "w": 25,
            "x": 0,
            "y": 115,
            "z": 144
          },
          {
            "h": 25,
            "l": 77,
            "w": 49,
            "x": 0,
            "y": 162,
            "z": 165
          },
          {
            "h": 25,
            "l": 49,
            "w": 77,
            "x": 0,
            "y": 0,
            "z": 174
          },
          {
            "h": 25,
            "l": 77,
            "w": 49,
            "x": 0,
            "y": 162,
            "z": 190
          },
          {
            "h": 25,
            "l": 77,
            "w": 49,
            "x": 84,
            "y": 0,
            "z": 0
          },
          {
            "h": 25,
            "l": 77,
            "w": 49,
            "x": 84,
            "y": 49,
            "z": 0
          },
          {
            "h": 25,
            "l": 77,
            "w": 49,
            "x": 84,
            "y": 98,
            "z": 0
          },
          {
            "h": 25,
            "l": 77,
            "w": 49,
            "x": 84,
            "y": 0,
            "z": 25
          },
          {
            "h": 25,
            "l": 77,
            "w": 49,
            "x": 84,
            "y": 49,
            "z": 25
          },
          {
            "h": 25,
            "l": 77,
            "w": 49,
            "x": 84,
            "y": 98,
            "z": 25
          },
          {
            "h": 25,
            "l": 77,
            "w": 49,
            "x": 84,
            "y": 0,
            "z": 50
          },
          {
            "h": 40,
            "l": 37,
            "w": 22,
            "x": 0,
            "y": 140,
            "z": 46
          },
          {
            "h": 40,
            "l": 37,
            "w": 22,
            "x": 0,
            "y": 140,
            "z": 86
          },
          {
            "h": 40,
            "l": 37,
            "w": 22,
            "x": 0,
            "y": 140,
            "z": 126
          },
          {
            "h": 40,
            "l": 37,
            "w": 22,
            "x": 0,
            "y": 140,
            "z": 166
          },
          {
            "h": 22,
            "l": 40,
            "w": 37,
            "x": 0,
            "y": 77,
            "z": 174
          },
          {
            "h": 22,
            "l": 40,
            "w": 37,
            "x": 0,
            "y": 77,
            "z": 196
          },
          {
            "h": 40,
            "l": 37,
            "w": 22,
            "x": 37,
            "y": 140,
            "z": 46
          },
          {
            "h": 40,
            "l": 37,
            "w": 22,
            "x": 37,
            "y": 140,
            "z": 86
          },
          {
            "h": 40,
            "l": 37,
            "w": 22,
            "x": 37,
            "y": 140,
            "z": 126
          },
          {
            "h": 40,
            "l": 37,
            "w": 22,
            "x": 37,
            "y": 140,
            "z": 166
          },
          {
            "h": 46,
            "l": 97,
            "w": 96,
            "x": 161,
            "y": 0,
            "z": 0
          },
          {
            "h": 46,
            "l": 97,
            "w": 96,
            "x": 161,
            "y": 96,
            "z": 0
          },
          {
            "h": 46,
            "l": 97,
            "w": 96,
            "x": 161,
            "y": 0,
            "z": 46
          },
          {
            "h": 46,
            "l": 97,
            "w": 96,
            "x": 161,
            "y": 96,
            "z": 46
          },
          {
            "h": 46,
            "l": 97,
            "w": 96,
            "x": 161,
            "y": 0,
            "z": 92
          },
          {
            "h": 46,
            "l": 97,
            "w": 96,
            "x": 161,
            "y": 96,
            "z": 92
          },
          {
            "h": 25,
            "l": 43,
            "w": 95,
            "x": 84,
            "y": 49,
            "z": 50
          },
          {
            "h": 25,
            "l": 43,
            "w": 95,
            "x": 84,
            "y": 0,
            "z": 75
          },
          {
            "h": 25,
            "l": 43,
            "w": 95,
            "x": 84,
            "y": 0,
            "z": 100
          },
          {
            "h": 25,
            "l": 43,
            "w": 95,
            "x": 84,
            "y": 0,
            "z": 125
          },
          {
            "h": 25,
            "l": 43,
            "w": 95,
            "x": 84,
            "y": 0,
            "z": 150
          },
          {
            "h": 25,
            "l": 43,
            "w": 95,
            "x": 84,
            "y": 0,
            "z": 175
          },
          {
            "h": 43,
            "l": 25,
            "w": 95,
            "x": 127,
            "y": 49,
            "z": 50
          },
          {
            "h": 43,
            "l": 25,
            "w": 95,
            "x": 127,
            "y": 49,
            "z": 93
          },
          {
            "h": 43,
            "l": 25,
            "w": 95,
            "x": 127,
            "y": 49,
            "z": 136
          },
          {
            "h": 43,
            "l": 95,
            "w": 25,
            "x": 161,
            "y": 192,
            "z": 0
          },
          {
            "h": 43,
            "l": 95,
            "w": 25,
            "x": 161,
            "y": 192,
            "z": 43
          },
          {
            "h": 43,
            "l": 95,
            "w": 25,
            "x": 161,
            "y": 192,
            "z": 86
          },
          {
            "h": 28,
            "l": 90,
            "w": 69,
            "x": 161,
            "y": 0,
            "z": 138
          },
          {
            "h": 28,
            "l": 90,
            "w": 69,
            "x": 161,
            "y": 69,
            "z": 138
          },
          {
            "h": 28,
            "l": 90,
            "w": 69,
            "x": 161,
            "y": 0,
            "z": 166
          },
          {
            "h": 28,
            "l": 90,
            "w": 69,
            "x": 161,
            "y": 69,
            "z": 166
          },
          {
            "h": 28,
            "l": 90,
            "w": 69,
            "x": 258,
            "y": 0,
            "z": 0
          },
          {
            "h": 28,
            "l": 90,
            "w": 69,
            "x": 258,
            "y": 69,
            "z": 0
          },
          {
            "h": 49,
            "l": 56,
            "w": 51,
            "x": 77,
            "y": 162,
            "z": 115
          },
          {
            "h": 49,
            "l": 56,
            "w": 51,
            "x": 77,
            "y": 162,
            "z": 164
          },
          {
            "h": 49,
            "l": 56,
            "w": 51,
            "x": 161,
            "y": 138,
            "z": 138
          },
          {
            "h": 80,
            "l": 118,
            "w": 93,
            "x": 258,
            "y": 138,
            "z": 0
          },
          {
            "h": 118,
            "l": 80,
            "w": 93,
            "x": 258,
            "y": 0,
            "z": 28
          },
          {
            "h": 80,
            "l": 118,
            "w": 93,
            "x": 258,
            "y": 138,
            "z": 80
          },
          {
            "h": 80,
            "l": 118,
            "w": 93,
            "x": 348,
            "y": 0,
            "z": 0
          },
          {
            "h": 80,
            "l": 118,
            "w": 93,
            "x": 348,
            "y": 0,
            "z": 80
          },
          {
            "h": 56,
            "l": 41,
            "w": 47,
            "x": 84,
            "y": 95,
            "z": 75
          },
          {
            "h": 56,
            "l": 41,
            "w": 47,
            "x": 84,
            "y": 95,
            "z": 131
          },
          {
            "h": 56,
            "l": 41,
            "w": 47,
            "x": 217,
            "y": 138,
            "z": 138
          },
          {
            "h": 56,
            "l": 47,
            "w": 41,
            "x": 258,
            "y": 93,
            "z": 28
          },
          {
            "h": 56,
            "l": 47,
            "w": 41,
            "x": 258,
            "y": 93,
            "z": 84
          },
          {
            "h": 27,
            "l": 78,
            "w": 71,
            "x": 258,
            "y": 0,
            "z": 146
          },
          {
            "h": 27,
            "l": 78,
            "w": 71,
            "x": 258,
            "y": 138,
            "z": 160
          },
          {
            "h": 27,
            "l": 78,
            "w": 71,
            "x": 258,
            "y": 0,
            "z": 173
          },
          {
            "h": 27,
            "l": 78,
            "w": 71,
            "x": 258,
            "y": 138,
            "z": 187
          },
          {
            "h": 27,
            "l": 78,
            "w": 71,
            "x": 348,
            "y": 0,
            "z": 160
          },
          {
            "h": 27,
            "l": 78,
            "w": 71,
            "x": 348,
            "y": 0,
            "z": 187
          },
          {
            "h": 27,
            "l": 78,
            "w": 71,
            "x": 376,
            "y": 138,
            "z": 0
          },
          {
            "h": 62,
            "l": 88,
            "w": 41,
            "x": 348,
            "y": 93,
            "z": 0
          },
          {
            "h": 62,
            "l": 88,
            "w": 41,
            "x": 348,
            "y": 93,
            "z": 62
          },
          {
            "h": 62,
            "l": 88,
            "w": 41,
            "x": 348,
            "y": 93,
            "z": 124
          },
          {
            "h": 62,
            "l": 88,
            "w": 41,
            "x": 436,
            "y": 93,
            "z": 0
          },
          {
            "h": 62,
            "l": 88,
            "w": 41,
            "x": 436,
            "y": 93,
            "z": 62
          },
          {
            "h": 62,
            "l": 88,
            "w": 41,
            "x": 436,
            "y": 93,
            "z": 124
          },
          {
            "h": 41,
            "l": 88,
            "w": 62,
            "x": 454,
            "y": 138,
            "z": 0
          },
          {
            "h": 41,
            "l": 88,
            "w": 62,
            "x": 454,
            "y": 138,
            "z": 41
          },
          {
            "h": 41,
            "l": 88,
            "w": 62,
            "x": 454,
            "y": 138,
            "z": 82
          },
          {
            "h": 41,
            "l": 88,
            "w": 62,
            "x": 454,
            "y": 138,
            "z": 123
          },
          {
            "h": 21,
            "l": 87,
            "w": 53,
            "x": 161,
            "y": 0,
            "z": 194
          },
          {
            "h": 21,
            "l": 87,
            "w": 53,
            "x": 161,
            "y": 53,
            "z": 194
          },
          {
            "h": 21,
            "l": 87,
            "w": 53,
            "x": 454,
            "y": 138,
            "z": 164
          },
          {
            "h": 21,
            "l": 87,
            "w": 53,
            "x": 454,
            "y": 138,
            "z": 185
          },
          {
            "h": 21,
            "l": 87,
            "w": 53,
            "x": 466,
            "y": 0,
            "z": 0
          },
          {
            "h": 21,
            "l": 87,
            "w": 53,
            "x": 466,
            "y": 0,
            "z": 21
          },
          {
            "h": 21,
            "l": 87,
            "w": 53,
            "x": 466,
            "y": 0,
            "z": 42
          },
          {
            "h": 21,
            "l": 87,
            "w": 53,
            "x": 466,
            "y": 0,
            "z": 63
          },
          {
            "h": 47,
            "l": 105,
            "w": 28,
            "x": 454,
            "y": 200,
            "z": 0
          },
          {
            "h": 47,
            "l": 105,
            "w": 28,
            "x": 454,
            "y": 200,
            "z": 47
          },
          {
            "h": 47,
            "l": 105,
            "w": 28,
            "x": 454,
            "y": 200,
            "z": 94
          },
          {
            "h": 47,
            "l": 105,
            "w": 28,
            "x": 454,
            "y": 200,
            "z": 141
          },
          {
            "h": 47,
            "l": 105,
            "w": 28,
            "x": 466,
            "y": 53,
            "z": 0
          },
          {
            "h": 47,
            "l": 105,
            "w": 28,
            "x": 466,
            "y": 53,
            "z": 47
          },
          {
            "h": 47,
            "l": 105,
            "w": 28,
            "x": 466,
            "y": 53,
            "z": 94
          },
          {
            "h": 47,
            "l": 105,
            "w": 28,
            "x": 466,
            "y": 53,
            "z": 141
          },
          {
            "h": 103,
            "l": 68,
            "w": 65,
            "x": 376,
            "y": 138,
            "z": 27
          },
          {
            "h": 31,
            "l": 67,
            "w": 64,
            "x": 376,
            "y": 138,
            "z": 130
          },
          {
            "h": 31,
            "l": 67,
            "w": 64,
            "x": 376,
            "y": 138,
            "z": 161
          },
          {
            "h": 27,
            "l": 37,
            "w": 83,
            "x": 336,
            "y": 138,
            "z": 160
          },
          {
            "h": 27,
            "l": 37,
            "w": 83,
            "x": 336,
            "y": 138,
            "z": 187
          },
          {
            "h": 27,
            "l": 83,
            "w": 37,
            "x": 348,
            "y": 93,
            "z": 186
          },
          {
            "h": 27,
            "l": 37,
            "w": 83,
            "x": 426,
            "y": 0,
            "z": 160
          },
          {
            "h": 27,
            "l": 37,
            "w": 83,
            "x": 426,
            "y": 0,
            "z": 187
          },
          {
            "h": 27,
            "l": 83,
            "w": 37,
            "x": 431,
            "y": 93,
            "z": 186
          },
          {
            "h": 27,
            "l": 83,
            "w": 37,
            "x": 466,
            "y": 0,
            "z": 84
          },
          {
            "h": 27,
            "l": 83,
            "w": 37,
            "x": 466,
            "y": 0,
            "z": 111
          },
          {
            "h": 44,
            "l": 31,
            "w": 29,
            "x": 40,
            "y": 77,
            "z": 174
          },
          {
            "h": 29,
            "l": 31,
            "w": 44,
            "x": 84,
            "y": 95,
            "z": 187
          },
          {
            "h": 29,
            "l": 31,
            "w": 44,
            "x": 127,
            "y": 0,
            "z": 75
          },
          {
            "h": 29,
            "l": 31,
            "w": 44,
            "x": 127,
            "y": 0,
            "z": 104
          },
          {
            "h": 29,
            "l": 31,
            "w": 44,
            "x": 127,
            "y": 0,
            "z": 133
          },
          {
            "h": 29,
            "l": 31,
            "w": 44,
            "x": 127,
            "y": 0,
            "z": 162
          },
          {
            "h": 29,
            "l": 31,
            "w": 44,
            "x": 127,
            "y": 0,
            "z": 191
          },
          {
            "h": 29,
            "l": 44,
            "w": 31,
            "x": 161,
            "y": 138,
            "z": 187
          },
          {
            "h": 29,
            "l": 44,
            "w": 31,
            "x": 258,
            "y": 93,
            "z": 140
          },
          {
            "h": 29,
            "l": 44,
            "w": 31,
            "x": 258,
            "y": 93,
            "z": 169
          }
        ],
        "container": {
          "H": 220,
          "L": 589,
          "W": 233
        }
      },
      "objectives": {
        "Z1": 0.716006,
        "Z2": 33,
        "Z3": 14.419734
      },
      "solution_id": "baseline"
    }
  ],
  "progress": {
    "per_generation": []
  },
  "run_id": "20251225_163001.015491_seed0_C1_respect",
  "schema_version": "1.0",
  "timestamp_utc": "2025-12-25T16:30:01.015491Z"
}
