{
  "algorithm": {
    "decoder": "DBLF",
    "name": "DBLF",
    "params": {
      "decoder": "DBLF",
      "rotation_mode": "six_way",
      "support_min_ratio": 1.0,
      "support_required": true
    },
    "seed": 0,
    "variant": "six_way"
  },
  "dataset": {
    "family": "BR-Original",
    "instance_id": "BR10_072",
    "modification_protocol": {
      "customer_assignment": null,
      "enabled": false,
      "fragile_assignment": null,
      "fragile_ratio": null,
      "n_customers": null,
      "notes": "",
      "orientation_rules": null,
      "seed": 0,
      "weight_limit": {
        "Qmax": null,
        "enabled": null,
        "note": ""
      },
      "weights": null
    },
    "source": "Bischoff-Ratcliff"
  },
  "meta": {
    "cg_summary": {
      "cg": [
        275.5378,
        104.3654,
        91.18
      ],
      "dev": [
        18.9622,
        12.1346,
        18.82
      ],
      "rd_pct": [
        6.4388,
        10.4159,
        17.1091
      ],
      "z1_util": 0.647768,
      "z3": 16.6389
    },
    "container": {
      "H": 220.0,
      "L": 589.0,
      "W": 233.0
    },
    "counts": {
      "placed": 85,
      "unplaced": 29
    },
    "notes": "",
    "timing": {
      "elapsed_sec": 0.241128
    }
  },
  "objectives": {
    "Z1": {
      "name": "volume_utilization",
      "sense": "max"
    },
    "Z2": {
      "name": "unloading_obstacles",
      "sense": "min"
    },
    "Z3": {
      "name": "cg_deviation_avg_axes",
      "sense": "min"
    }
  },
  "pareto_front": [
    {
      "cg": {
        "container": {
          "x": 294.5,
          "y": 116.5,
          "z": 110.0
        },
        "dev": {
          "x": 18.9622,
          "y": 12.1346,
          "z": 18.82
        },
        "loaded": {
          "x": 275.5378,
          "y": 104.3654,
          "z": 91.18
        },
        "rd_pct": {
          "x": 6.4388,
          "y": 10.4159,
          "z": 17.1091
        },
        "total_mass": 19557502.0,
        "z3": 16.6389
      },
      "diagnostics": {
        "elapsed_sec": 0.241128,
        "notes": "",
        "placed_count": 85,
        "unplaced_count": 29
      },
      "layout": {
        "boxes": [
          {
            "h": 68,
            "l": 96,
            "w": 95,
            "x": 0,
            "y": 0,
            "z": 0
          },
          {
            "h": 68,
            "l": 96,
            "w": 95,
            "x": 0,
            "y": 95,
            "z": 0
          },
          {
            "h": 61,
            "l": 69,
            "w": 35,
            "x": 0,
            "y": 190,
            "z": 0
          },
          {
            "h": 61,
            "l": 69,
            "w": 35,
            "x": 0,
            "y": 190,
            "z": 61
          },
          {
            "h": 55,
            "l": 70,
            "w": 107,
            "x": 0,
            "y": 0,
            "z": 68
          },
          {
            "h": 107,
            "l": 70,
            "w": 55,
            "x": 0,
            "y": 107,
            "z": 68
          },
          {
            "h": 55,
            "l": 70,
            "w": 107,
            "x": 0,
            "y": 0,
            "z": 123
          },
          {
            "h": 55,
            "l": 107,
            "w": 70,
            "x": 96,
            "y": 0,
            "z": 0
          },
          {
            "h": 85,
            "l": 92,
            "w": 34,
            "x": 69,
            "y": 190,
            "z": 0
          },
          {
            "h": 96,
            "l": 60,
            "w": 31,
            "x": 0,
            "y": 190,
            "z": 122
          },
          {
            "h": 38,
            "l": 66,
            "w": 38,
            "x": 0,
            "y": 107,
            "z": 175
          },
          {
            "h": 38,
            "l": 66,
            "w": 38,
            "x": 0,
            "y": 0,
            "z": 178
          },
          {
            "h": 36,
            "l": 63,
            "w": 57,
            "x": 0,
            "y": 38,
            "z": 178
          },
          {
            "h": 36,
            "l": 63,
            "w": 57,
            "x": 96,
            "y": 70,
            "z": 0
          },
          {
            "h": 36,
            "l": 63,
            "w": 57,
            "x": 96,
            "y": 127,
            "z": 0
          },
          {
            "h": 31,
            "l": 51,
            "w": 31,
            "x": 69,
            "y": 190,
            "z": 85
          },
          {
            "h": 31,
            "l": 51,
            "w": 31,
            "x": 69,
            "y": 190,
            "z": 116
          },
          {
            "h": 31,
            "l": 51,
            "w": 31,
            "x": 69,
            "y": 190,
            "z": 147
          },
          {
            "h": 75,
            "l": 44,
            "w": 100,
            "x": 96,
            "y": 70,
            "z": 36
          },
          {
            "h": 53,
            "l": 78,
            "w": 66,
            "x": 96,
            "y": 0,
            "z": 55
          },
          {
            "h": 53,
            "l": 78,
            "w": 66,
            "x": 96,
            "y": 0,
            "z": 108
          },
          {
            "h": 32,
            "l": 33,
            "w": 29,
            "x": 69,
            "y": 190,
            "z": 178
          },
          {
            "h": 29,
            "l": 33,
            "w": 32,
            "x": 96,
            "y": 70,
            "z": 111
          },
          {
            "h": 29,
            "l": 33,
            "w": 32,
            "x": 96,
            "y": 102,
            "z": 111
          },
          {
            "h": 45,
            "l": 81,
            "w": 72,
            "x": 159,
            "y": 70,
            "z": 0
          },
          {
            "h": 57,
            "l": 88,
            "w": 38,
            "x": 159,
            "y": 142,
            "z": 0
          },
          {
            "h": 34,
            "l": 52,
            "w": 21,
            "x": 0,
            "y": 162,
            "z": 68
          },
          {
            "h": 112,
            "l": 69,
            "w": 31,
            "x": 159,
            "y": 70,
            "z": 45
          },
          {
            "h": 112,
            "l": 69,
            "w": 31,
            "x": 159,
            "y": 101,
            "z": 45
          },
          {
            "h": 112,
            "l": 69,
            "w": 31,
            "x": 159,
            "y": 142,
            "z": 57
          },
          {
            "h": 69,
            "l": 112,
            "w": 31,
            "x": 161,
            "y": 190,
            "z": 0
          },
          {
            "h": 57,
            "l": 63,
            "w": 59,
            "x": 96,
            "y": 0,
            "z": 161
          },
          {
            "h": 57,
            "l": 63,
            "w": 59,
            "x": 159,
            "y": 70,
            "z": 157
          },
          {
            "h": 57,
            "l": 63,
            "w": 59,
            "x": 203,
            "y": 0,
            "z": 0
          },
          {
            "h": 57,
            "l": 63,
            "w": 59,
            "x": 203,
            "y": 0,
            "z": 57
          },
          {
            "h": 48,
            "l": 76,
            "w": 65,
            "x": 240,
            "y": 70,
            "z": 0
          },
          {
            "h": 48,
            "l": 76,
            "w": 65,
            "x": 240,
            "y": 70,
            "z": 48
          },
          {
            "h": 48,
            "l": 76,
            "w": 65,
            "x": 240,
            "y": 70,
            "z": 96
          },
          {
            "h": 92,
            "l": 60,
            "w": 46,
            "x": 203,
            "y": 0,
            "z": 114
          },
          {
            "h": 52,
            "l": 118,
            "w": 55,
            "x": 266,
            "y": 0,
            "z": 0
          },
          {
            "h": 93,
            "l": 22,
            "w": 96,
            "x": 70,
            "y": 0,
            "z": 68
          },
          {
            "h": 96,
            "l": 22,
            "w": 93,
            "x": 70,
            "y": 96,
            "z": 68
          },
          {
            "h": 93,
            "l": 96,
            "w": 22,
            "x": 161,
            "y": 190,
            "z": 69
          },
          {
            "h": 93,
            "l": 96,
            "w": 22,
            "x": 247,
            "y": 142,
            "z": 0
          },
          {
            "h": 93,
            "l": 96,
            "w": 22,
            "x": 247,
            "y": 164,
            "z": 0
          },
          {
            "h": 93,
            "l": 96,
            "w": 22,
            "x": 247,
            "y": 142,
            "z": 93
          },
          {
            "h": 93,
            "l": 96,
            "w": 22,
            "x": 247,
            "y": 164,
            "z": 93
          },
          {
            "h": 73,
            "l": 32,
            "w": 29,
            "x": 96,
            "y": 134,
            "z": 111
          },
          {
            "h": 73,
            "l": 32,
            "w": 29,
            "x": 96,
            "y": 70,
            "z": 140
          },
          {
            "h": 73,
            "l": 32,
            "w": 29,
            "x": 96,
            "y": 99,
            "z": 140
          },
          {
            "h": 73,
            "l": 32,
            "w": 29,
            "x": 120,
            "y": 190,
            "z": 85
          },
          {
            "h": 78,
            "l": 104,
            "w": 54,
            "x": 266,
            "y": 0,
            "z": 52
          },
          {
            "h": 78,
            "l": 104,
            "w": 54,
            "x": 266,
            "y": 0,
            "z": 130
          },
          {
            "h": 78,
            "l": 104,
            "w": 54,
            "x": 316,
            "y": 70,
            "z": 0
          },
          {
            "h": 78,
            "l": 104,
            "w": 54,
            "x": 316,
            "y": 70,
            "z": 78
          },
          {
            "h": 80,
            "l": 120,
            "w": 26,
            "x": 273,
            "y": 190,
            "z": 0
          },
          {
            "h": 80,
            "l": 120,
            "w": 26,
            "x": 273,
            "y": 190,
            "z": 80
          },
          {
            "h": 46,
            "l": 58,
            "w": 54,
            "x": 240,
            "y": 70,
            "z": 144
          },
          {
            "h": 46,
            "l": 58,
            "w": 54,
            "x": 316,
            "y": 70,
            "z": 156
          },
          {
            "h": 90,
            "l": 90,
            "w": 40,
            "x": 343,
            "y": 142,
            "z": 0
          },
          {
            "h": 90,
            "l": 90,
            "w": 40,
            "x": 343,
            "y": 142,
            "z": 90
          },
          {
            "h": 55,
            "l": 79,
            "w": 58,
            "x": 384,
            "y": 0,
            "z": 0
          },
          {
            "h": 55,
            "l": 79,
            "w": 58,
            "x": 384,
            "y": 0,
            "z": 55
          },
          {
            "h": 45,
            "l": 22,
            "w": 74,
            "x": 70,
            "y": 0,
            "z": 161
          },
          {
            "h": 102,
            "l": 72,
            "w": 35,
            "x": 384,
            "y": 0,
            "z": 110
          },
          {
            "h": 72,
            "l": 102,
            "w": 35,
            "x": 393,
            "y": 190,
            "z": 0
          },
          {
            "h": 78,
            "l": 84,
            "w": 67,
            "x": 420,
            "y": 70,
            "z": 0
          },
          {
            "h": 78,
            "l": 84,
            "w": 67,
            "x": 420,
            "y": 70,
            "z": 78
          },
          {
            "h": 78,
            "l": 84,
            "w": 67,
            "x": 463,
            "y": 0,
            "z": 0
          },
          {
            "h": 58,
            "l": 98,
            "w": 44,
            "x": 374,
            "y": 70,
            "z": 156
          },
          {
            "h": 58,
            "l": 98,
            "w": 44,
            "x": 433,
            "y": 142,
            "z": 0
          },
          {
            "h": 58,
            "l": 98,
            "w": 44,
            "x": 433,
            "y": 142,
            "z": 58
          },
          {
            "h": 97,
            "l": 83,
            "w": 56,
            "x": 463,
            "y": 0,
            "z": 78
          },
          {
            "h": 97,
            "l": 83,
            "w": 56,
            "x": 504,
            "y": 70,
            "z": 0
          },
          {
            "h": 57,
            "l": 67,
            "w": 38,
            "x": 433,
            "y": 142,
            "z": 116
          },
          {
            "h": 57,
            "l": 67,
            "w": 38,
            "x": 495,
            "y": 190,
            "z": 0
          },
          {
            "h": 57,
            "l": 67,
            "w": 38,
            "x": 495,
            "y": 190,
            "z": 57
          },
          {
            "h": 48,
            "l": 79,
            "w": 35,
            "x": 393,
            "y": 190,
            "z": 72
          },
          {
            "h": 66,
            "l": 75,
            "w": 43,
            "x": 504,
            "y": 70,
            "z": 97
          },
          {
            "h": 104,
            "l": 53,
            "w": 36,
            "x": 495,
            "y": 190,
            "z": 114
          },
          {
            "h": 104,
            "l": 53,
            "w": 36,
            "x": 531,
            "y": 142,
            "z": 0
          },
          {
            "h": 104,
            "l": 53,
            "w": 36,
            "x": 531,
            "y": 142,
            "z": 104
          },
          {
            "h": 93,
            "l": 41,
            "w": 43,
            "x": 547,
            "y": 0,
            "z": 0
          },
          {
            "h": 82,
            "l": 26,
            "w": 48,
            "x": 174,
            "y": 0,
            "z": 55
          },
          {
            "h": 82,
            "l": 26,
            "w": 48,
            "x": 174,
            "y": 0,
            "z": 137
          }
        ],
        "container": {
          "H": 220,
          "L": 589,
          "W": 233
        }
      },
      "objectives": {
        "Z1": 0.647768,
        "Z2": 29,
        "Z3": 16.638922
      },
      "solution_id": "baseline"
    }
  ],
  "progress": {
    "per_generation": []
  },
  "run_id": "20251225_163248.610249_seed0_six_way",
  "schema_version": "1.0",
  "timestamp_utc": "2025-12-25T16:32:48.610249Z"
}
