{
  "algorithm": {
    "decoder": "DBLF",
    "name": "DBLF",
    "params": {
      "decoder": "DBLF",
      "rotation_mode": "C1_respect",
      "support_min_ratio": 1.0,
      "support_required": true
    },
    "seed": 0,
    "variant": "C1_respect"
  },
  "dataset": {
    "family": "BR-Original",
    "instance_id": "BR9_026",
    "modification_protocol": {
      "customer_assignment": null,
      "enabled": false,
      "fragile_assignment": null,
      "fragile_ratio": null,
      "n_customers": null,
      "notes": "",
      "orientation_rules": null,
      "seed": 0,
      "weight_limit": {
        "Qmax": null,
        "enabled": null,
        "note": ""
      },
      "weights": null
    },
    "source": "Bischoff-Ratcliff"
  },
  "meta": {
    "cg_summary": {
      "cg": [
        283.7538,
        102.1412,
        93.1107
      ],
      "dev": [
        10.7462,
        14.3588,
        16.8893
      ],
      "rd_pct": [
        3.649,
        12.3252,
        15.3539
      ],
      "z1_util": 0.656119,
      "z3": 13.9981
    },
    "container": {
      "H": 220.0,
      "L": 589.0,
      "W": 233.0
    },
    "counts": {
      "placed": 100,
      "unplaced": 45
    },
    "notes": "",
    "timing": {
      "elapsed_sec": 0.3185
    }
  },
  "objectives": {
    "Z1": {
      "name": "volume_utilization",
      "sense": "max"
    },
    "Z2": {
      "name": "unloading_obstacles",
      "sense": "min"
    },
    "Z3": {
      "name": "cg_deviation_avg_axes",
      "sense": "min"
    }
  },
  "pareto_front": [
    {
      "cg": {
        "container": {
          "x": 294.5,
          "y": 116.5,
          "z": 110.0
        },
        "dev": {
          "x": 10.7462,
          "y": 14.3588,
          "z": 16.8893
        },
        "loaded": {
          "x": 283.7538,
          "y": 102.1412,
          "z": 93.1107
        },
        "rd_pct": {
          "x": 3.649,
          "y": 12.3252,
          "z": 15.3539
        },
        "total_mass": 19809643.0,
        "z3": 13.9981
      },
      "diagnostics": {
        "elapsed_sec": 0.3185,
        "notes": "",
        "placed_count": 100,
        "unplaced_count": 45
      },
      "layout": {
        "boxes": [
          {
            "h": 41,
            "l": 86,
            "w": 71,
            "x": 0,
            "y": 0,
            "z": 0
          },
          {
            "h": 41,
            "l": 86,
            "w": 71,
            "x": 0,
            "y": 71,
            "z": 0
          },
          {
            "h": 41,
            "l": 86,
            "w": 71,
            "x": 0,
            "y": 142,
            "z": 0
          },
          {
            "h": 41,
            "l": 86,
            "w": 71,
            "x": 0,
            "y": 0,
            "z": 41
          },
          {
            "h": 41,
            "l": 86,
            "w": 71,
            "x": 0,
            "y": 71,
            "z": 41
          },
          {
            "h": 58,
            "l": 75,
            "w": 58,
            "x": 0,
            "y": 142,
            "z": 41
          },
          {
            "h": 58,
            "l": 75,
            "w": 58,
            "x": 0,
            "y": 0,
            "z": 82
          },
          {
            "h": 58,
            "l": 75,
            "w": 58,
            "x": 0,
            "y": 58,
            "z": 82
          },
          {
            "h": 58,
            "l": 75,
            "w": 58,
            "x": 0,
            "y": 142,
            "z": 99
          },
          {
            "h": 58,
            "l": 75,
            "w": 58,
            "x": 0,
            "y": 0,
            "z": 140
          },
          {
            "h": 58,
            "l": 75,
            "w": 58,
            "x": 0,
            "y": 58,
            "z": 140
          },
          {
            "h": 58,
            "l": 75,
            "w": 58,
            "x": 0,
            "y": 142,
            "z": 157
          },
          {
            "h": 27,
            "l": 100,
            "w": 81,
            "x": 86,
            "y": 0,
            "z": 0
          },
          {
            "h": 27,
            "l": 100,
            "w": 81,
            "x": 86,
            "y": 81,
            "z": 0
          },
          {
            "h": 27,
            "l": 100,
            "w": 81,
            "x": 86,
            "y": 0,
            "z": 27
          },
          {
            "h": 42,
            "l": 59,
            "w": 24,
            "x": 0,
            "y": 116,
            "z": 82
          },
          {
            "h": 42,
            "l": 59,
            "w": 24,
            "x": 0,
            "y": 116,
            "z": 124
          },
          {
            "h": 42,
            "l": 59,
            "w": 24,
            "x": 0,
            "y": 116,
            "z": 166
          },
          {
            "h": 24,
            "l": 59,
            "w": 42,
            "x": 86,
            "y": 162,
            "z": 0
          },
          {
            "h": 42,
            "l": 59,
            "w": 24,
            "x": 86,
            "y": 204,
            "z": 0
          },
          {
            "h": 30,
            "l": 69,
            "w": 37,
            "x": 86,
            "y": 81,
            "z": 27
          },
          {
            "h": 30,
            "l": 69,
            "w": 37,
            "x": 86,
            "y": 118,
            "z": 27
          },
          {
            "h": 30,
            "l": 69,
            "w": 37,
            "x": 86,
            "y": 0,
            "z": 54
          },
          {
            "h": 30,
            "l": 69,
            "w": 37,
            "x": 86,
            "y": 37,
            "z": 54
          },
          {
            "h": 63,
            "l": 50,
            "w": 36,
            "x": 86,
            "y": 162,
            "z": 24
          },
          {
            "h": 36,
            "l": 63,
            "w": 50,
            "x": 86,
            "y": 81,
            "z": 57
          },
          {
            "h": 34,
            "l": 96,
            "w": 72,
            "x": 186,
            "y": 0,
            "z": 0
          },
          {
            "h": 34,
            "l": 96,
            "w": 72,
            "x": 186,
            "y": 72,
            "z": 0
          },
          {
            "h": 34,
            "l": 96,
            "w": 72,
            "x": 186,
            "y": 144,
            "z": 0
          },
          {
            "h": 34,
            "l": 96,
            "w": 72,
            "x": 186,
            "y": 0,
            "z": 34
          },
          {
            "h": 34,
            "l": 96,
            "w": 72,
            "x": 186,
            "y": 72,
            "z": 34
          },
          {
            "h": 29,
            "l": 71,
            "w": 111,
            "x": 186,
            "y": 0,
            "z": 68
          },
          {
            "h": 29,
            "l": 71,
            "w": 111,
            "x": 186,
            "y": 0,
            "z": 97
          },
          {
            "h": 29,
            "l": 71,
            "w": 111,
            "x": 186,
            "y": 0,
            "z": 126
          },
          {
            "h": 29,
            "l": 71,
            "w": 111,
            "x": 186,
            "y": 0,
            "z": 155
          },
          {
            "h": 29,
            "l": 71,
            "w": 111,
            "x": 186,
            "y": 0,
            "z": 184
          },
          {
            "h": 102,
            "l": 67,
            "w": 53,
            "x": 86,
            "y": 0,
            "z": 84
          },
          {
            "h": 102,
            "l": 67,
            "w": 53,
            "x": 186,
            "y": 144,
            "z": 34
          },
          {
            "h": 53,
            "l": 102,
            "w": 67,
            "x": 282,
            "y": 0,
            "z": 0
          },
          {
            "h": 32,
            "l": 34,
            "w": 71,
            "x": 145,
            "y": 162,
            "z": 0
          },
          {
            "h": 32,
            "l": 34,
            "w": 71,
            "x": 145,
            "y": 162,
            "z": 32
          },
          {
            "h": 32,
            "l": 34,
            "w": 71,
            "x": 145,
            "y": 162,
            "z": 64
          },
          {
            "h": 32,
            "l": 34,
            "w": 71,
            "x": 145,
            "y": 162,
            "z": 96
          },
          {
            "h": 32,
            "l": 34,
            "w": 71,
            "x": 145,
            "y": 162,
            "z": 128
          },
          {
            "h": 53,
            "l": 88,
            "w": 75,
            "x": 282,
            "y": 67,
            "z": 0
          },
          {
            "h": 53,
            "l": 88,
            "w": 75,
            "x": 282,
            "y": 142,
            "z": 0
          },
          {
            "h": 53,
            "l": 88,
            "w": 75,
            "x": 282,
            "y": 0,
            "z": 53
          },
          {
            "h": 42,
            "l": 50,
            "w": 46,
            "x": 86,
            "y": 81,
            "z": 93
          },
          {
            "h": 42,
            "l": 50,
            "w": 46,
            "x": 86,
            "y": 81,
            "z": 135
          },
          {
            "h": 42,
            "l": 50,
            "w": 46,
            "x": 86,
            "y": 81,
            "z": 177
          },
          {
            "h": 41,
            "l": 84,
            "w": 70,
            "x": 282,
            "y": 75,
            "z": 53
          },
          {
            "h": 41,
            "l": 84,
            "w": 70,
            "x": 282,
            "y": 145,
            "z": 53
          },
          {
            "h": 44,
            "l": 48,
            "w": 98,
            "x": 282,
            "y": 75,
            "z": 94
          },
          {
            "h": 44,
            "l": 48,
            "w": 98,
            "x": 282,
            "y": 75,
            "z": 138
          },
          {
            "h": 25,
            "l": 54,
            "w": 43,
            "x": 86,
            "y": 0,
            "z": 186
          },
          {
            "h": 63,
            "l": 61,
            "w": 49,
            "x": 186,
            "y": 144,
            "z": 136
          },
          {
            "h": 49,
            "l": 63,
            "w": 61,
            "x": 282,
            "y": 0,
            "z": 106
          },
          {
            "h": 49,
            "l": 63,
            "w": 61,
            "x": 282,
            "y": 0,
            "z": 155
          },
          {
            "h": 49,
            "l": 63,
            "w": 61,
            "x": 370,
            "y": 67,
            "z": 0
          },
          {
            "h": 49,
            "l": 63,
            "w": 61,
            "x": 370,
            "y": 128,
            "z": 0
          },
          {
            "h": 49,
            "l": 63,
            "w": 61,
            "x": 370,
            "y": 67,
            "z": 49
          },
          {
            "h": 96,
            "l": 106,
            "w": 51,
            "x": 384,
            "y": 0,
            "z": 0
          },
          {
            "h": 96,
            "l": 106,
            "w": 51,
            "x": 384,
            "y": 0,
            "z": 96
          },
          {
            "h": 51,
            "l": 106,
            "w": 96,
            "x": 433,
            "y": 67,
            "z": 0
          },
          {
            "h": 96,
            "l": 106,
            "w": 51,
            "x": 433,
            "y": 163,
            "z": 0
          },
          {
            "h": 51,
            "l": 106,
            "w": 96,
            "x": 433,
            "y": 67,
            "z": 51
          },
          {
            "h": 96,
            "l": 106,
            "w": 51,
            "x": 433,
            "y": 163,
            "z": 96
          },
          {
            "h": 51,
            "l": 106,
            "w": 96,
            "x": 433,
            "y": 67,
            "z": 102
          },
          {
            "h": 51,
            "l": 106,
            "w": 96,
            "x": 433,
            "y": 67,
            "z": 153
          },
          {
            "h": 26,
            "l": 97,
            "w": 64,
            "x": 490,
            "y": 0,
            "z": 0
          },
          {
            "h": 26,
            "l": 97,
            "w": 64,
            "x": 490,
            "y": 0,
            "z": 26
          },
          {
            "h": 39,
            "l": 29,
            "w": 68,
            "x": 145,
            "y": 162,
            "z": 160
          },
          {
            "h": 39,
            "l": 29,
            "w": 68,
            "x": 155,
            "y": 81,
            "z": 27
          },
          {
            "h": 68,
            "l": 62,
            "w": 39,
            "x": 282,
            "y": 173,
            "z": 94
          },
          {
            "h": 68,
            "l": 62,
            "w": 39,
            "x": 370,
            "y": 189,
            "z": 0
          },
          {
            "h": 68,
            "l": 62,
            "w": 39,
            "x": 370,
            "y": 128,
            "z": 49
          },
          {
            "h": 68,
            "l": 62,
            "w": 39,
            "x": 370,
            "y": 189,
            "z": 68
          },
          {
            "h": 38,
            "l": 25,
            "w": 100,
            "x": 257,
            "y": 0,
            "z": 68
          },
          {
            "h": 38,
            "l": 25,
            "w": 100,
            "x": 257,
            "y": 0,
            "z": 106
          },
          {
            "h": 38,
            "l": 25,
            "w": 100,
            "x": 257,
            "y": 0,
            "z": 144
          },
          {
            "h": 26,
            "l": 91,
            "w": 53,
            "x": 490,
            "y": 0,
            "z": 52
          },
          {
            "h": 26,
            "l": 91,
            "w": 53,
            "x": 490,
            "y": 0,
            "z": 78
          },
          {
            "h": 22,
            "l": 74,
            "w": 72,
            "x": 0,
            "y": 0,
            "z": 198
          },
          {
            "h": 74,
            "l": 61,
            "w": 51,
            "x": 370,
            "y": 67,
            "z": 98
          },
          {
            "h": 74,
            "l": 61,
            "w": 51,
            "x": 490,
            "y": 0,
            "z": 104
          },
          {
            "h": 61,
            "l": 31,
            "w": 67,
            "x": 155,
            "y": 0,
            "z": 54
          },
          {
            "h": 61,
            "l": 31,
            "w": 67,
            "x": 155,
            "y": 0,
            "z": 115
          },
          {
            "h": 61,
            "l": 67,
            "w": 31,
            "x": 186,
            "y": 111,
            "z": 68
          },
          {
            "h": 61,
            "l": 67,
            "w": 31,
            "x": 186,
            "y": 111,
            "z": 129
          },
          {
            "h": 61,
            "l": 31,
            "w": 67,
            "x": 330,
            "y": 75,
            "z": 94
          },
          {
            "h": 61,
            "l": 31,
            "w": 67,
            "x": 330,
            "y": 75,
            "z": 155
          },
          {
            "h": 61,
            "l": 31,
            "w": 67,
            "x": 539,
            "y": 67,
            "z": 0
          },
          {
            "h": 27,
            "l": 43,
            "w": 73,
            "x": 282,
            "y": 75,
            "z": 182
          },
          {
            "h": 55,
            "l": 62,
            "w": 33,
            "x": 282,
            "y": 173,
            "z": 162
          },
          {
            "h": 62,
            "l": 55,
            "w": 33,
            "x": 370,
            "y": 128,
            "z": 117
          },
          {
            "h": 43,
            "l": 51,
            "w": 46,
            "x": 370,
            "y": 67,
            "z": 172
          },
          {
            "h": 43,
            "l": 46,
            "w": 51,
            "x": 539,
            "y": 134,
            "z": 0
          },
          {
            "h": 51,
            "l": 46,
            "w": 43,
            "x": 539,
            "y": 185,
            "z": 0
          },
          {
            "h": 27,
            "l": 99,
            "w": 36,
            "x": 384,
            "y": 0,
            "z": 192
          },
          {
            "h": 27,
            "l": 99,
            "w": 36,
            "x": 433,
            "y": 163,
            "z": 192
          }
        ],
        "container": {
          "H": 220,
          "L": 589,
          "W": 233
        }
      },
      "objectives": {
        "Z1": 0.656119,
        "Z2": 45,
        "Z3": 13.998121
      },
      "solution_id": "baseline"
    }
  ],
  "progress": {
    "per_generation": []
  },
  "run_id": "20251225_163203.550054_seed0_C1_respect",
  "schema_version": "1.0",
  "timestamp_utc": "2025-12-25T16:32:03.550054Z"
}
