{
  "algorithm": {
    "decoder": "DBLF",
    "name": "DBLF",
    "params": {
      "decoder": "DBLF",
      "rotation_mode": "C1_respect",
      "support_min_ratio": 1.0,
      "support_required": true
    },
    "seed": 0,
    "variant": "C1_respect"
  },
  "dataset": {
    "family": "BR-Original",
    "instance_id": "BR8_095",
    "modification_protocol": {
      "customer_assignment": null,
      "enabled": false,
      "fragile_assignment": null,
      "fragile_ratio": null,
      "n_customers": null,
      "notes": "",
      "orientation_rules": null,
      "seed": 0,
      "weight_limit": {
        "Qmax": null,
        "enabled": null,
        "note": ""
      },
      "weights": null
    },
    "source": "Bischoff-Ratcliff"
  },
  "meta": {
    "cg_summary": {
      "cg": [
        295.2448,
        99.3001,
        93.6015
      ],
      "dev": [
        0.7448,
        17.1999,
        16.3985
      ],
      "rd_pct": [
        0.2529,
        14.7638,
        14.9077
      ],
      "z1_util": 0.627771,
      "z3": 11.4477
    },
    "container": {
      "H": 220.0,
      "L": 589.0,
      "W": 233.0
    },
    "counts": {
      "placed": 98,
      "unplaced": 38
    },
    "notes": "",
    "timing": {
      "elapsed_sec": 0.282645
    }
  },
  "objectives": {
    "Z1": {
      "name": "volume_utilization",
      "sense": "max"
    },
    "Z2": {
      "name": "unloading_obstacles",
      "sense": "min"
    },
    "Z3": {
      "name": "cg_deviation_avg_axes",
      "sense": "min"
    }
  },
  "pareto_front": [
    {
      "cg": {
        "container": {
          "x": 294.5,
          "y": 116.5,
          "z": 110.0
        },
        "dev": {
          "x": 0.7448,
          "y": 17.1999,
          "z": 16.3985
        },
        "loaded": {
          "x": 295.2448,
          "y": 99.3001,
          "z": 93.6015
        },
        "rd_pct": {
          "x": 0.2529,
          "y": 14.7638,
          "z": 14.9077
        },
        "total_mass": 18953752.0,
        "z3": 11.4477
      },
      "diagnostics": {
        "elapsed_sec": 0.282645,
        "notes": "",
        "placed_count": 98,
        "unplaced_count": 38
      },
      "layout": {
        "boxes": [
          {
            "h": 20,
            "l": 101,
            "w": 69,
            "x": 0,
            "y": 0,
            "z": 0
          },
          {
            "h": 20,
            "l": 101,
            "w": 69,
            "x": 0,
            "y": 69,
            "z": 0
          },
          {
            "h": 20,
            "l": 101,
            "w": 69,
            "x": 0,
            "y": 138,
            "z": 0
          },
          {
            "h": 54,
            "l": 66,
            "w": 108,
            "x": 0,
            "y": 0,
            "z": 20
          },
          {
            "h": 54,
            "l": 66,
            "w": 108,
            "x": 0,
            "y": 0,
            "z": 74
          },
          {
            "h": 54,
            "l": 66,
            "w": 108,
            "x": 0,
            "y": 0,
            "z": 128
          },
          {
            "h": 54,
            "l": 108,
            "w": 66,
            "x": 101,
            "y": 0,
            "z": 0
          },
          {
            "h": 54,
            "l": 108,
            "w": 66,
            "x": 101,
            "y": 66,
            "z": 0
          },
          {
            "h": 54,
            "l": 108,
            "w": 66,
            "x": 101,
            "y": 132,
            "z": 0
          },
          {
            "h": 33,
            "l": 74,
            "w": 62,
            "x": 0,
            "y": 108,
            "z": 20
          },
          {
            "h": 62,
            "l": 74,
            "w": 33,
            "x": 0,
            "y": 170,
            "z": 20
          },
          {
            "h": 33,
            "l": 74,
            "w": 62,
            "x": 0,
            "y": 108,
            "z": 53
          },
          {
            "h": 62,
            "l": 74,
            "w": 33,
            "x": 0,
            "y": 170,
            "z": 82
          },
          {
            "h": 33,
            "l": 69,
            "w": 61,
            "x": 0,
            "y": 108,
            "z": 86
          },
          {
            "h": 33,
            "l": 69,
            "w": 61,
            "x": 0,
            "y": 108,
            "z": 119
          },
          {
            "h": 61,
            "l": 69,
            "w": 33,
            "x": 0,
            "y": 170,
            "z": 144
          },
          {
            "h": 33,
            "l": 69,
            "w": 61,
            "x": 0,
            "y": 108,
            "z": 152
          },
          {
            "h": 33,
            "l": 61,
            "w": 69,
            "x": 0,
            "y": 0,
            "z": 182
          },
          {
            "h": 31,
            "l": 71,
            "w": 64,
            "x": 101,
            "y": 0,
            "z": 54
          },
          {
            "h": 31,
            "l": 71,
            "w": 64,
            "x": 101,
            "y": 64,
            "z": 54
          },
          {
            "h": 31,
            "l": 71,
            "w": 64,
            "x": 101,
            "y": 128,
            "z": 54
          },
          {
            "h": 31,
            "l": 71,
            "w": 64,
            "x": 101,
            "y": 0,
            "z": 85
          },
          {
            "h": 31,
            "l": 71,
            "w": 64,
            "x": 101,
            "y": 64,
            "z": 85
          },
          {
            "h": 30,
            "l": 38,
            "w": 32,
            "x": 0,
            "y": 69,
            "z": 182
          },
          {
            "h": 30,
            "l": 38,
            "w": 32,
            "x": 0,
            "y": 108,
            "z": 185
          },
          {
            "h": 32,
            "l": 30,
            "w": 38,
            "x": 38,
            "y": 108,
            "z": 185
          },
          {
            "h": 30,
            "l": 32,
            "w": 38,
            "x": 66,
            "y": 0,
            "z": 20
          },
          {
            "h": 37,
            "l": 47,
            "w": 108,
            "x": 101,
            "y": 0,
            "z": 116
          },
          {
            "h": 37,
            "l": 47,
            "w": 108,
            "x": 101,
            "y": 0,
            "z": 153
          },
          {
            "h": 47,
            "l": 37,
            "w": 108,
            "x": 172,
            "y": 0,
            "z": 54
          },
          {
            "h": 47,
            "l": 37,
            "w": 108,
            "x": 172,
            "y": 0,
            "z": 101
          },
          {
            "h": 47,
            "l": 37,
            "w": 108,
            "x": 172,
            "y": 0,
            "z": 148
          },
          {
            "h": 36,
            "l": 100,
            "w": 41,
            "x": 209,
            "y": 0,
            "z": 0
          },
          {
            "h": 36,
            "l": 100,
            "w": 41,
            "x": 209,
            "y": 41,
            "z": 0
          },
          {
            "h": 36,
            "l": 100,
            "w": 41,
            "x": 209,
            "y": 82,
            "z": 0
          },
          {
            "h": 39,
            "l": 99,
            "w": 79,
            "x": 209,
            "y": 123,
            "z": 0
          },
          {
            "h": 39,
            "l": 99,
            "w": 79,
            "x": 209,
            "y": 0,
            "z": 36
          },
          {
            "h": 22,
            "l": 83,
            "w": 55,
            "x": 209,
            "y": 123,
            "z": 39
          },
          {
            "h": 22,
            "l": 83,
            "w": 55,
            "x": 209,
            "y": 123,
            "z": 61
          },
          {
            "h": 49,
            "l": 99,
            "w": 36,
            "x": 209,
            "y": 79,
            "z": 36
          },
          {
            "h": 36,
            "l": 99,
            "w": 49,
            "x": 209,
            "y": 0,
            "z": 75
          },
          {
            "h": 49,
            "l": 99,
            "w": 36,
            "x": 209,
            "y": 79,
            "z": 85
          },
          {
            "h": 36,
            "l": 99,
            "w": 49,
            "x": 209,
            "y": 0,
            "z": 111
          },
          {
            "h": 49,
            "l": 99,
            "w": 36,
            "x": 209,
            "y": 79,
            "z": 134
          },
          {
            "h": 36,
            "l": 99,
            "w": 49,
            "x": 209,
            "y": 0,
            "z": 147
          },
          {
            "h": 36,
            "l": 99,
            "w": 49,
            "x": 209,
            "y": 0,
            "z": 183
          },
          {
            "h": 36,
            "l": 99,
            "w": 49,
            "x": 308,
            "y": 123,
            "z": 0
          },
          {
            "h": 22,
            "l": 83,
            "w": 56,
            "x": 308,
            "y": 172,
            "z": 0
          },
          {
            "h": 22,
            "l": 83,
            "w": 56,
            "x": 308,
            "y": 172,
            "z": 22
          },
          {
            "h": 22,
            "l": 83,
            "w": 56,
            "x": 308,
            "y": 172,
            "z": 44
          },
          {
            "h": 22,
            "l": 83,
            "w": 56,
            "x": 308,
            "y": 172,
            "z": 66
          },
          {
            "h": 44,
            "l": 66,
            "w": 52,
            "x": 101,
            "y": 128,
            "z": 85
          },
          {
            "h": 44,
            "l": 66,
            "w": 52,
            "x": 101,
            "y": 128,
            "z": 129
          },
          {
            "h": 44,
            "l": 66,
            "w": 52,
            "x": 101,
            "y": 128,
            "z": 173
          },
          {
            "h": 44,
            "l": 66,
            "w": 52,
            "x": 209,
            "y": 123,
            "z": 83
          },
          {
            "h": 44,
            "l": 66,
            "w": 52,
            "x": 209,
            "y": 123,
            "z": 127
          },
          {
            "h": 29,
            "l": 120,
            "w": 69,
            "x": 309,
            "y": 0,
            "z": 0
          },
          {
            "h": 29,
            "l": 120,
            "w": 69,
            "x": 309,
            "y": 0,
            "z": 29
          },
          {
            "h": 29,
            "l": 120,
            "w": 69,
            "x": 309,
            "y": 0,
            "z": 58
          },
          {
            "h": 90,
            "l": 101,
            "w": 50,
            "x": 309,
            "y": 69,
            "z": 0
          },
          {
            "h": 90,
            "l": 101,
            "w": 50,
            "x": 309,
            "y": 0,
            "z": 87
          },
          {
            "h": 90,
            "l": 101,
            "w": 50,
            "x": 309,
            "y": 69,
            "z": 90
          },
          {
            "h": 90,
            "l": 101,
            "w": 50,
            "x": 391,
            "y": 172,
            "z": 0
          },
          {
            "h": 90,
            "l": 101,
            "w": 50,
            "x": 391,
            "y": 172,
            "z": 90
          },
          {
            "h": 50,
            "l": 101,
            "w": 90,
            "x": 410,
            "y": 69,
            "z": 0
          },
          {
            "h": 58,
            "l": 54,
            "w": 39,
            "x": 308,
            "y": 123,
            "z": 36
          },
          {
            "h": 39,
            "l": 58,
            "w": 54,
            "x": 308,
            "y": 172,
            "z": 88
          },
          {
            "h": 58,
            "l": 54,
            "w": 39,
            "x": 308,
            "y": 123,
            "z": 94
          },
          {
            "h": 39,
            "l": 58,
            "w": 54,
            "x": 308,
            "y": 172,
            "z": 127
          },
          {
            "h": 58,
            "l": 54,
            "w": 39,
            "x": 308,
            "y": 123,
            "z": 152
          },
          {
            "h": 58,
            "l": 88,
            "w": 64,
            "x": 410,
            "y": 69,
            "z": 50
          },
          {
            "h": 58,
            "l": 88,
            "w": 64,
            "x": 410,
            "y": 69,
            "z": 108
          },
          {
            "h": 58,
            "l": 88,
            "w": 64,
            "x": 429,
            "y": 0,
            "z": 0
          },
          {
            "h": 58,
            "l": 88,
            "w": 64,
            "x": 429,
            "y": 0,
            "z": 58
          },
          {
            "h": 58,
            "l": 88,
            "w": 64,
            "x": 429,
            "y": 0,
            "z": 116
          },
          {
            "h": 46,
            "l": 82,
            "w": 52,
            "x": 410,
            "y": 69,
            "z": 166
          },
          {
            "h": 46,
            "l": 82,
            "w": 52,
            "x": 429,
            "y": 0,
            "z": 174
          },
          {
            "h": 46,
            "l": 82,
            "w": 52,
            "x": 492,
            "y": 172,
            "z": 0
          },
          {
            "h": 46,
            "l": 82,
            "w": 52,
            "x": 492,
            "y": 172,
            "z": 46
          },
          {
            "h": 46,
            "l": 82,
            "w": 52,
            "x": 492,
            "y": 172,
            "z": 92
          },
          {
            "h": 46,
            "l": 82,
            "w": 52,
            "x": 492,
            "y": 172,
            "z": 138
          },
          {
            "h": 53,
            "l": 63,
            "w": 63,
            "x": 511,
            "y": 69,
            "z": 0
          },
          {
            "h": 53,
            "l": 63,
            "w": 63,
            "x": 511,
            "y": 69,
            "z": 53
          },
          {
            "h": 53,
            "l": 63,
            "w": 63,
            "x": 511,
            "y": 69,
            "z": 106
          },
          {
            "h": 53,
            "l": 63,
            "w": 63,
            "x": 511,
            "y": 69,
            "z": 159
          },
          {
            "h": 82,
            "l": 67,
            "w": 60,
            "x": 517,
            "y": 0,
            "z": 0
          },
          {
            "h": 82,
            "l": 67,
            "w": 60,
            "x": 517,
            "y": 0,
            "z": 82
          },
          {
            "h": 40,
            "l": 52,
            "w": 49,
            "x": 209,
            "y": 123,
            "z": 171
          },
          {
            "h": 40,
            "l": 52,
            "w": 49,
            "x": 308,
            "y": 172,
            "z": 166
          },
          {
            "h": 39,
            "l": 48,
            "w": 44,
            "x": 309,
            "y": 0,
            "z": 177
          },
          {
            "h": 39,
            "l": 48,
            "w": 44,
            "x": 309,
            "y": 69,
            "z": 180
          },
          {
            "h": 39,
            "l": 48,
            "w": 44,
            "x": 357,
            "y": 0,
            "z": 177
          },
          {
            "h": 27,
            "l": 53,
            "w": 21,
            "x": 0,
            "y": 207,
            "z": 0
          },
          {
            "h": 27,
            "l": 53,
            "w": 21,
            "x": 0,
            "y": 207,
            "z": 27
          },
          {
            "h": 27,
            "l": 53,
            "w": 21,
            "x": 0,
            "y": 207,
            "z": 54
          },
          {
            "h": 65,
            "l": 44,
            "w": 48,
            "x": 362,
            "y": 123,
            "z": 36
          },
          {
            "h": 65,
            "l": 44,
            "w": 48,
            "x": 362,
            "y": 123,
            "z": 101
          },
          {
            "h": 44,
            "l": 65,
            "w": 48,
            "x": 517,
            "y": 0,
            "z": 164
          }
        ],
        "container": {
          "H": 220,
          "L": 589,
          "W": 233
        }
      },
      "objectives": {
        "Z1": 0.627771,
        "Z2": 38,
        "Z3": 11.447729
      },
      "solution_id": "baseline"
    }
  ],
  "progress": {
    "per_generation": []
  },
  "run_id": "20251225_163119.526988_seed0_C1_respect",
  "schema_version": "1.0",
  "timestamp_utc": "2025-12-25T16:31:19.526988Z"
}
